networkx_query/__init__.py
networkx_query/definition.py
networkx_query/operator.py
networkx_query/parser.py
networkx_query/query.py
networkx_query/relationship.py
networkx_query/utils.py
networkx_query-2.1.3.dist-info/METADATA
networkx_query-2.1.3.dist-info/WHEEL
networkx_query-2.1.3.dist-info/top_level.txt
networkx_query-2.1.3.dist-info/RECORD
