Metadata-Version: 2.2
Name: networkx_query
Version: 2.1.3
Summary: NetworkX Query Tool
Author-email: Jerome Guibert <jguibert@gmail.com>
License: The MIT License (MIT)
Project-URL: homepage, https://pypi.org/project/networkx_query
Project-URL: documentation, https://geronimo-iia.github.io/networkx-query/
Project-URL: repository, https://github.com/geronimo-iia/networkx-query
Keywords: networkx,graph,query
Classifier: Development Status :: 5 - Production/Stable
Classifier: Intended Audience :: Developers
Classifier: License :: OSI Approved :: MIT License
Classifier: Natural Language :: English
Classifier: Programming Language :: Python
Classifier: Programming Language :: Python :: 3
Classifier: Programming Language :: Python :: 3.9
Classifier: Programming Language :: Python :: 3.10
Classifier: Programming Language :: Python :: 3.11
Classifier: Programming Language :: Python :: 3.12
Classifier: Topic :: Software Development :: Libraries :: Python Modules
Classifier: Typing :: Typed
Requires-Python: <4,>=3.9
Requires-Dist: networkx
